metrics/__init__.py
metrics/cli.py
metrics/exceptions/__init__.py
metrics/exceptions/exceptions.py
metrics/main.py
metrics/types/__init__.py
metrics/types/base.py
metrics/types/enums.py
metrics/utils/__init__.py
metrics/utils/runners.py
abstract_metrics-0.1.0.dev5.dist-info/LICENSE
abstract_metrics-0.1.0.dev5.dist-info/METADATA
abstract_metrics-0.1.0.dev5.dist-info/WHEEL
abstract_metrics-0.1.0.dev5.dist-info/RECORD
