Metadata-Version: 2.1
Name: abstract-metrics
Version: 0.1.0.dev5
Summary: A lightweight framework for defining arbitrary business metrics as Python code.
License: MIT
Author: Fraser
Author-email: fraserisbester@gmail.com
Requires-Python: >=3.11,<4.0
Classifier: License :: OSI Approved :: MIT License
Classifier: Programming Language :: Python :: 3
Classifier: Programming Language :: Python :: 3.11
